sadif/__init__.py
sadif/cli.py
sadif/clientmanager/__init__.py
sadif/clientmanager/client_data_export.py
sadif/clientmanager/client_data_import.py
sadif/clientmanager/client_data_manager.py
sadif/config/__init__.py
sadif/config/soar_config.py
sadif/dataconfig/__init__.py
sadif/dataconfig/variables.json
sadif/frameworks_drivers/__init__.py
sadif/frameworks_drivers/crawler/__init__.py
sadif/frameworks_drivers/crawler/base_crawler/__init__.py
sadif/frameworks_drivers/crawler/crawler_data_export.py
sadif/frameworks_drivers/crawler/crawler_data_import.py
sadif/frameworks_drivers/crawler/crawler_manager.py
sadif/frameworks_drivers/gitmanager/__init__.py
sadif/frameworks_drivers/log_manager/__init__.py
sadif/frameworks_drivers/log_manager/soar_log.py
sadif/frameworks_drivers/modules_manager/__init__.py
sadif/frameworks_drivers/notification/__init__.py
sadif/frameworks_drivers/notification/webhook.py
sadif/frameworks_drivers/soar_yara/__init__.py
sadif/frameworks_drivers/soar_yara/yara_compiler.py
sadif/frameworks_drivers/soar_yara/yara_crud.py
sadif/frameworks_drivers/soar_yara/yara_export.py
sadif/frameworks_drivers/soar_yara/yara_import.py
sadif/frameworks_drivers/ticket_system/__init__.py
sadif/frameworks_drivers/ticket_system/thehive/__init__.py
sadif/frameworks_drivers/ticket_system/thehive/thehive_internal_mods_api/__init__.py
sadif/frameworks_drivers/ticket_system/thehive/thehive_internal_mods_api/caso_de_uso/__init__.py
sadif/frameworks_drivers/ticket_system/thehive/thehive_internal_mods_api/caso_de_uso/caselist.py
sadif/frameworks_drivers/ticket_system/thehive/thehive_internal_mods_api/thehive_datatype/__init__.py
sadif/frameworks_drivers/ticket_system/thehive/thehive_internal_mods_api/thehive_manager_alert/__init__.py
sadif/frameworks_drivers/ticket_system/thehive/thehive_internal_mods_api/thehive_manager_case/__init__.py
sadif/frameworks_drivers/ticket_system/thehive/thehive_internal_mods_api/thehive_manager_case/case_response.py
sadif-0.2.0.dist-info/LICENSE
sadif-0.2.0.dist-info/METADATA
sadif-0.2.0.dist-info/WHEEL
sadif-0.2.0.dist-info/RECORD
